littlefs/__init__.py
littlefs/__main__.py
littlefs/context.py
littlefs/errors.py
littlefs/lfs.cp311-win_amd64.pyd
littlefs/lfs.pyi
littlefs/py.typed
littlefs/repl.py
littlefs_python-0.17.0.dist-info/licenses/LICENSE
littlefs_python-0.17.0.dist-info/METADATA
littlefs_python-0.17.0.dist-info/WHEEL
littlefs_python-0.17.0.dist-info/entry_points.txt
littlefs_python-0.17.0.dist-info/top_level.txt
littlefs_python-0.17.0.dist-info/RECORD
